MockingBirdOnlyForUse/__init__.py
MockingBirdOnlyForUse/encoder/__init__.py
MockingBirdOnlyForUse/encoder/audio.py
MockingBirdOnlyForUse/encoder/inference.py
MockingBirdOnlyForUse/encoder/model.py
MockingBirdOnlyForUse/encoder/params_data.py
MockingBirdOnlyForUse/encoder/params_model.py
MockingBirdOnlyForUse/logger.py
MockingBirdOnlyForUse/raw_use.py
MockingBirdOnlyForUse/synthesizer/__init__.py
MockingBirdOnlyForUse/synthesizer/audio.py
MockingBirdOnlyForUse/synthesizer/gst_hyperparameters.py
MockingBirdOnlyForUse/synthesizer/hparams.py
MockingBirdOnlyForUse/synthesizer/inference.py
MockingBirdOnlyForUse/synthesizer/models/global_style_token.py
MockingBirdOnlyForUse/synthesizer/models/tacotron.py
MockingBirdOnlyForUse/synthesizer/utils/__init__.py
MockingBirdOnlyForUse/synthesizer/utils/cleaners.py
MockingBirdOnlyForUse/synthesizer/utils/numbers.py
MockingBirdOnlyForUse/synthesizer/utils/symbols.py
MockingBirdOnlyForUse/synthesizer/utils/text.py
MockingBirdOnlyForUse/utils/__init__.py
MockingBirdOnlyForUse/utils/argutils.py
MockingBirdOnlyForUse/utils/logmmse.py
MockingBirdOnlyForUse/utils/modelutils.py
MockingBirdOnlyForUse/vocoder/display.py
MockingBirdOnlyForUse/vocoder/distribution.py
MockingBirdOnlyForUse/vocoder/hifigan/config_16k_.json
MockingBirdOnlyForUse/vocoder/hifigan/env.py
MockingBirdOnlyForUse/vocoder/hifigan/inference.py
MockingBirdOnlyForUse/vocoder/hifigan/meldataset.py
MockingBirdOnlyForUse/vocoder/hifigan/models.py
MockingBirdOnlyForUse/vocoder/hifigan/utils.py
MockingBirdOnlyForUse/vocoder/LICENSE.txt
MockingBirdOnlyForUse/vocoder/vocoder_dataset.py
MockingBirdOnlyForUse/vocoder/wavernn/audio.py
MockingBirdOnlyForUse/vocoder/wavernn/hparams.py
MockingBirdOnlyForUse/vocoder/wavernn/inference.py
MockingBirdOnlyForUse/vocoder/wavernn/models/fatchord_version.py
mockingbirdonlyforuse-0.0.10.dist-info/LICENSE.txt
mockingbirdonlyforuse-0.0.10.dist-info/WHEEL
mockingbirdonlyforuse-0.0.10.dist-info/METADATA
mockingbirdonlyforuse-0.0.10.dist-info/RECORD
