Metadata-Version: 2.1
Name: mockingbirdonlyforuse
Version: 0.0.10
Summary: A Raw Use Version for MockingBird
Home-page: https://github.com/babysor/MockingBird
License: LICENSE
Keywords: MockingBird,python
Author: Alex Newton
Author-email: sharenfan222@gmail.com
Requires-Python: >=3.9,<4.0
Classifier: License :: Other/Proprietary License
Classifier: Programming Language :: Python :: 3
Classifier: Programming Language :: Python :: 3.10
Classifier: Programming Language :: Python :: 3.9
Requires-Dist: SoundFile
Requires-Dist: Unidecode
Requires-Dist: inflect
Requires-Dist: librosa (==0.8.1)
Requires-Dist: matplotlib
Requires-Dist: numpy (==1.19.3); sys_platform == "win32"
Requires-Dist: numpy (==1.19.4); sys_platform != "win32"
Requires-Dist: pypinyin
Requires-Dist: scipy
Requires-Dist: webrtcvad-wheels
Project-URL: Repository, https://github.com/Diaosi1111/MockingBirdOnlyForUse
